belogging/__init__.py
belogging/defaults.py
belogging/exceptions.py
belogging/filters.py
belogging/loader.py
belogging-0.2.0.dist-info/METADATA
belogging-0.2.0.dist-info/WHEEL
belogging-0.2.0.dist-info/licenses/LICENSE
belogging-0.2.0.dist-info/RECORD
