Metadata-Version: 2.4
Name: belogging
Version: 0.2.0
Summary: Easy and opinionated logging configuration for Python apps
Project-URL: Github, https://github.com/georgeyk/belogging/
Project-URL: Releases, https://github.com/georgeyk/belogging/releases
Author-email: "George Y. Kussumoto" <contato@georgeyk.com.br>
License: MIT License
License-File: LICENSE
Keywords: logging
Classifier: Development Status :: 4 - Beta
Classifier: Environment :: Console
Classifier: Intended Audience :: Developers
Classifier: License :: OSI Approved :: MIT License
Classifier: Natural Language :: English
Classifier: Operating System :: OS Independent
Classifier: Programming Language :: Python :: 3 :: Only
Classifier: Programming Language :: Python :: 3.10
Classifier: Programming Language :: Python :: 3.11
Classifier: Programming Language :: Python :: 3.12
Classifier: Topic :: System :: Logging
Requires-Python: >=3.10
Requires-Dist: python-json-logger>=3.2.0
